build_nextjs_app/main.py
build_nextjs_app-1.0.2.dist-info/entry_points.txt
build_nextjs_app-1.0.2.dist-info/LICENSE
build_nextjs_app-1.0.2.dist-info/METADATA
build_nextjs_app-1.0.2.dist-info/WHEEL
build_nextjs_app-1.0.2.dist-info/RECORD
