Metadata-Version: 2.1
Name: build_nextjs_app
Version: 1.0.2
Summary: A simple tool for building NextJS applications faster.
Author: Ryan Partridge
Author-email: rpartridge101@gmail.com
Requires-Python: >=3.12,<4.0
Classifier: Programming Language :: Python :: 3
Classifier: Programming Language :: Python :: 3.12
Requires-Dist: typer[all] (>=0.12.3,<0.13.0)
